{"version":"20260717-a97029fceaf39797","cinemaId":"0007","programmingDate":"2026-07-21","sessions":[{"CinemaId":"0007","ScheduledFilmId":"HO00015724","SessionId":"195912","Showtime":"2026-07-21T12:30:00+00:00","SourceDate":"2026-07-21","SourceProgrammingDate":"2026-07-21","ScreenName":"STANDARD","SeatsAvailable":66,"SessionAttributesNames":["STANDARD"],"TimeSlot":"Afternoon","Status":"","ExperienceCode":"STD","IsAvailableForOffer":false,"Comment":""},{"CinemaId":"0007","ScheduledFilmId":"HO00015724","SessionId":"195913","Showtime":"2026-07-21T14:45:00+00:00","SourceDate":"2026-07-21","SourceProgrammingDate":"2026-07-21","ScreenName":"STANDARD","SeatsAvailable":173,"SessionAttributesNames":["STANDARD"],"TimeSlot":"Afternoon","Status":"","ExperienceCode":"STD","IsAvailableForOffer":false,"Comment":""},{"CinemaId":"0007","ScheduledFilmId":"HO00015724","SessionId":"195914","Showtime":"2026-07-21T17:00:00+00:00","SourceDate":"2026-07-21","SourceProgrammingDate":"2026-07-21","ScreenName":"STANDARD","SeatsAvailable":156,"SessionAttributesNames":["STANDARD"],"TimeSlot":"Primetime","Status":"","ExperienceCode":"STD","IsAvailableForOffer":false,"Comment":""},{"CinemaId":"0007","ScheduledFilmId":"HO00015724","SessionId":"195915","Showtime":"2026-07-21T19:15:00+00:00","SourceDate":"2026-07-21","SourceProgrammingDate":"2026-07-21","ScreenName":"STANDARD","SeatsAvailable":135,"SessionAttributesNames":["STANDARD"],"TimeSlot":"Primetime","Status":"","ExperienceCode":"STD","IsAvailableForOffer":false,"Comment":""},{"CinemaId":"0007","ScheduledFilmId":"HO00015756","SessionId":"196044","Showtime":"2026-07-21T12:00:00+00:00","SourceDate":"2026-07-21","SourceProgrammingDate":"2026-07-21","ScreenName":"STANDARD","SeatsAvailable":159,"SessionAttributesNames":["STANDARD"],"TimeSlot":"Afternoon","Status":"","ExperienceCode":"STD","IsAvailableForOffer":false,"Comment":""},{"CinemaId":"0007","ScheduledFilmId":"HO00015756","SessionId":"196045","Showtime":"2026-07-21T14:15:00+00:00","SourceDate":"2026-07-21","SourceProgrammingDate":"2026-07-21","ScreenName":"STANDARD","SeatsAvailable":83,"SessionAttributesNames":["STANDARD"],"TimeSlot":"Afternoon","Status":"","ExperienceCode":"STD","IsAvailableForOffer":false,"Comment":""},{"CinemaId":"0007","ScheduledFilmId":"HO00015756","SessionId":"196046","Showtime":"2026-07-21T16:30:00+00:00","SourceDate":"2026-07-21","SourceProgrammingDate":"2026-07-21","ScreenName":"STANDARD","SeatsAvailable":140,"SessionAttributesNames":["STANDARD"],"TimeSlot":"Afternoon","Status":"","ExperienceCode":"STD","IsAvailableForOffer":false,"Comment":""},{"CinemaId":"0007","ScheduledFilmId":"HO00015756","SessionId":"196047","Showtime":"2026-07-21T18:45:00+00:00","SourceDate":"2026-07-21","SourceProgrammingDate":"2026-07-21","ScreenName":"STANDARD","SeatsAvailable":64,"SessionAttributesNames":["STANDARD"],"TimeSlot":"Primetime","Status":"","ExperienceCode":"STD","IsAvailableForOffer":false,"Comment":""},{"CinemaId":"0007","ScheduledFilmId":"HO00015858","SessionId":"195978","Showtime":"2026-07-21T12:00:00+00:00","SourceDate":"2026-07-21","SourceProgrammingDate":"2026-07-21","ScreenName":"STANDARD","SeatsAvailable":152,"SessionAttributesNames":["STANDARD"],"TimeSlot":"Afternoon","Status":"","ExperienceCode":"STD","IsAvailableForOffer":false,"Comment":""},{"CinemaId":"0007","ScheduledFilmId":"HO00015858","SessionId":"195948","Showtime":"2026-07-21T13:15:00+00:00","SourceDate":"2026-07-21","SourceProgrammingDate":"2026-07-21","ScreenName":"STANDARD","SeatsAvailable":142,"SessionAttributesNames":["STANDARD"],"TimeSlot":"Afternoon","Status":"","ExperienceCode":"STD","IsAvailableForOffer":false,"Comment":""},{"CinemaId":"0007","ScheduledFilmId":"HO00015858","SessionId":"195949","Showtime":"2026-07-21T15:45:00+00:00","SourceDate":"2026-07-21","SourceProgrammingDate":"2026-07-21","ScreenName":"STANDARD","SeatsAvailable":113,"SessionAttributesNames":["STANDARD"],"TimeSlot":"Afternoon","Status":"","ExperienceCode":"STD","IsAvailableForOffer":false,"Comment":""},{"CinemaId":"0007","ScheduledFilmId":"HO00015858","SessionId":"195950","Showtime":"2026-07-21T18:15:00+00:00","SourceDate":"2026-07-21","SourceProgrammingDate":"2026-07-21","ScreenName":"STANDARD","SeatsAvailable":158,"SessionAttributesNames":["STANDARD"],"TimeSlot":"Primetime","Status":"","ExperienceCode":"STD","IsAvailableForOffer":false,"Comment":""},{"CinemaId":"0007","ScheduledFilmId":"HO00015858","SessionId":"195951","Showtime":"2026-07-21T20:45:00+00:00","SourceDate":"2026-07-21","SourceProgrammingDate":"2026-07-21","ScreenName":"STANDARD","SeatsAvailable":173,"SessionAttributesNames":["STANDARD"],"TimeSlot":"Primetime","Status":"","ExperienceCode":"STD","IsAvailableForOffer":false,"Comment":""},{"CinemaId":"0007","ScheduledFilmId":"HO00015967","SessionId":"196006","Showtime":"2026-07-21T14:00:00+00:00","SourceDate":"2026-07-21","SourceProgrammingDate":"2026-07-21","ScreenName":"STANDARD","SeatsAvailable":134,"SessionAttributesNames":["STANDARD"],"TimeSlot":"Afternoon","Status":"","ExperienceCode":"STD","IsAvailableForOffer":false,"Comment":""},{"CinemaId":"0007","ScheduledFilmId":"HO00015967","SessionId":"195916","Showtime":"2026-07-21T21:20:00+00:00","SourceDate":"2026-07-21","SourceProgrammingDate":"2026-07-21","ScreenName":"STANDARD","SeatsAvailable":45,"SessionAttributesNames":["STANDARD"],"TimeSlot":"Primetime","Status":"","ExperienceCode":"STD","IsAvailableForOffer":false,"Comment":""},{"CinemaId":"0007","ScheduledFilmId":"HO00015967","SessionId":"195917","Showtime":"2026-07-21T23:45:00+00:00","SourceDate":"2026-07-21","SourceProgrammingDate":"2026-07-21","ScreenName":"STANDARD","SeatsAvailable":163,"SessionAttributesNames":["STANDARD"],"TimeSlot":"LateNight","Status":"","ExperienceCode":"STD","IsAvailableForOffer":false,"Comment":""},{"CinemaId":"0007","ScheduledFilmId":"HO00015994","SessionId":"195952","Showtime":"2026-07-21T23:15:00+00:00","SourceDate":"2026-07-21","SourceProgrammingDate":"2026-07-21","ScreenName":"STANDARD","SeatsAvailable":67,"SessionAttributesNames":["STANDARD"],"TimeSlot":"LateNight","Status":"","ExperienceCode":"STD","IsAvailableForOffer":false,"Comment":""},{"CinemaId":"0007","ScheduledFilmId":"HO00016187","SessionId":"196008","Showtime":"2026-07-21T19:35:00+00:00","SourceDate":"2026-07-21","SourceProgrammingDate":"2026-07-21","ScreenName":"STANDARD","SeatsAvailable":119,"SessionAttributesNames":["STANDARD"],"TimeSlot":"Primetime","Status":"","ExperienceCode":"STD","IsAvailableForOffer":false,"Comment":""},{"CinemaId":"0007","ScheduledFilmId":"HO00016191","SessionId":"196007","Showtime":"2026-07-21T16:25:00+00:00","SourceDate":"2026-07-21","SourceProgrammingDate":"2026-07-21","ScreenName":"STANDARD","SeatsAvailable":84,"SessionAttributesNames":["STANDARD"],"TimeSlot":"Afternoon","Status":"","ExperienceCode":"STD","IsAvailableForOffer":false,"Comment":""},{"CinemaId":"0007","ScheduledFilmId":"HO00016191","SessionId":"196009","Showtime":"2026-07-21T22:45:00+00:00","SourceDate":"2026-07-21","SourceProgrammingDate":"2026-07-21","ScreenName":"STANDARD","SeatsAvailable":168,"SessionAttributesNames":["STANDARD"],"TimeSlot":"Primetime","Status":"","ExperienceCode":"STD","IsAvailableForOffer":false,"Comment":""},{"CinemaId":"0007","ScheduledFilmId":"HO00016335","SessionId":"196048","Showtime":"2026-07-21T21:00:00+00:00","SourceDate":"2026-07-21","SourceProgrammingDate":"2026-07-21","ScreenName":"STANDARD","SeatsAvailable":82,"SessionAttributesNames":["STANDARD"],"TimeSlot":"Primetime","Status":"","ExperienceCode":"STD","IsAvailableForOffer":false,"Comment":""},{"CinemaId":"0007","ScheduledFilmId":"HO00016335","SessionId":"196049","Showtime":"2026-07-21T23:15:00+00:00","SourceDate":"2026-07-21","SourceProgrammingDate":"2026-07-21","ScreenName":"STANDARD","SeatsAvailable":72,"SessionAttributesNames":["STANDARD"],"TimeSlot":"LateNight","Status":"","ExperienceCode":"STD","IsAvailableForOffer":false,"Comment":""},{"CinemaId":"0007","ScheduledFilmId":"HO00016339","SessionId":"195850","Showtime":"2026-07-21T12:30:00+00:00","SourceDate":"2026-07-21","SourceProgrammingDate":"2026-07-21","ScreenName":"STANDARD","SeatsAvailable":155,"SessionAttributesNames":["STANDARD"],"TimeSlot":"Afternoon","Status":"","ExperienceCode":"STD","IsAvailableForOffer":false,"Comment":""},{"CinemaId":"0007","ScheduledFilmId":"HO00016339","SessionId":"195979","Showtime":"2026-07-21T14:30:00+00:00","SourceDate":"2026-07-21","SourceProgrammingDate":"2026-07-21","ScreenName":"STANDARD","SeatsAvailable":107,"SessionAttributesNames":["STANDARD"],"TimeSlot":"Afternoon","Status":"","ExperienceCode":"STD","IsAvailableForOffer":false,"Comment":""},{"CinemaId":"0007","ScheduledFilmId":"HO00016339","SessionId":"195824","Showtime":"2026-07-21T15:00:00+00:00","SourceDate":"2026-07-21","SourceProgrammingDate":"2026-07-21","ScreenName":"STANDARD","SeatsAvailable":75,"SessionAttributesNames":["STANDARD"],"TimeSlot":"Afternoon","Status":"","ExperienceCode":"STD","IsAvailableForOffer":false,"Comment":""},{"CinemaId":"0007","ScheduledFilmId":"HO00016339","SessionId":"195851","Showtime":"2026-07-21T16:00:00+00:00","SourceDate":"2026-07-21","SourceProgrammingDate":"2026-07-21","ScreenName":"STANDARD","SeatsAvailable":91,"SessionAttributesNames":["STANDARD"],"TimeSlot":"Afternoon","Status":"","ExperienceCode":"STD","IsAvailableForOffer":false,"Comment":""},{"CinemaId":"0007","ScheduledFilmId":"HO00016339","SessionId":"195980","Showtime":"2026-07-21T18:00:00+00:00","SourceDate":"2026-07-21","SourceProgrammingDate":"2026-07-21","ScreenName":"STANDARD","SeatsAvailable":110,"SessionAttributesNames":["STANDARD"],"TimeSlot":"Primetime","Status":"","ExperienceCode":"STD","IsAvailableForOffer":false,"Comment":""},{"CinemaId":"0007","ScheduledFilmId":"HO00016339","SessionId":"195825","Showtime":"2026-07-21T18:30:00+00:00","SourceDate":"2026-07-21","SourceProgrammingDate":"2026-07-21","ScreenName":"STANDARD","SeatsAvailable":136,"SessionAttributesNames":["STANDARD"],"TimeSlot":"Primetime","Status":"","ExperienceCode":"STD","IsAvailableForOffer":false,"Comment":""},{"CinemaId":"0007","ScheduledFilmId":"HO00016339","SessionId":"195852","Showtime":"2026-07-21T19:30:00+00:00","SourceDate":"2026-07-21","SourceProgrammingDate":"2026-07-21","ScreenName":"STANDARD","SeatsAvailable":72,"SessionAttributesNames":["STANDARD"],"TimeSlot":"Primetime","Status":"","ExperienceCode":"STD","IsAvailableForOffer":false,"Comment":""},{"CinemaId":"0007","ScheduledFilmId":"HO00016339","SessionId":"195981","Showtime":"2026-07-21T21:30:00+00:00","SourceDate":"2026-07-21","SourceProgrammingDate":"2026-07-21","ScreenName":"STANDARD","SeatsAvailable":147,"SessionAttributesNames":["STANDARD"],"TimeSlot":"Primetime","Status":"","ExperienceCode":"STD","IsAvailableForOffer":false,"Comment":""},{"CinemaId":"0007","ScheduledFilmId":"HO00016339","SessionId":"195826","Showtime":"2026-07-21T22:00:00+00:00","SourceDate":"2026-07-21","SourceProgrammingDate":"2026-07-21","ScreenName":"STANDARD","SeatsAvailable":86,"SessionAttributesNames":["STANDARD"],"TimeSlot":"Primetime","Status":"","ExperienceCode":"STD","IsAvailableForOffer":false,"Comment":""},{"CinemaId":"0007","ScheduledFilmId":"HO00016339","SessionId":"195853","Showtime":"2026-07-21T23:00:00+00:00","SourceDate":"2026-07-21","SourceProgrammingDate":"2026-07-21","ScreenName":"STANDARD","SeatsAvailable":81,"SessionAttributesNames":["STANDARD"],"TimeSlot":"LateNight","Status":"","ExperienceCode":"STD","IsAvailableForOffer":false,"Comment":""}]}
