{"version":"20260718-e66cf4192d7cf97d","cinemaId":"0007","programmingDate":"2026-08-04","sessions":[{"CinemaId":"0007","ScheduledFilmId":"HO00015860","SessionId":"195281","Showtime":"2026-08-04T13:30:00+00:00","SourceDate":"2026-08-04","SourceProgrammingDate":"2026-08-04","ScreenName":"STANDARD","SeatsAvailable":179,"SessionAttributesNames":["STANDARD"],"TimeSlot":"Afternoon","Status":"","ExperienceCode":"STD","IsAvailableForOffer":false,"Comment":""},{"CinemaId":"0007","ScheduledFilmId":"HO00015860","SessionId":"195313","Showtime":"2026-08-04T14:30:00+00:00","SourceDate":"2026-08-04","SourceProgrammingDate":"2026-08-04","ScreenName":"STANDARD","SeatsAvailable":55,"SessionAttributesNames":["STANDARD"],"TimeSlot":"Afternoon","Status":"","ExperienceCode":"STD","IsAvailableForOffer":false,"Comment":""},{"CinemaId":"0007","ScheduledFilmId":"HO00015860","SessionId":"195282","Showtime":"2026-08-04T16:30:00+00:00","SourceDate":"2026-08-04","SourceProgrammingDate":"2026-08-04","ScreenName":"STANDARD","SeatsAvailable":47,"SessionAttributesNames":["STANDARD"],"TimeSlot":"Afternoon","Status":"","ExperienceCode":"STD","IsAvailableForOffer":false,"Comment":""},{"CinemaId":"0007","ScheduledFilmId":"HO00015860","SessionId":"195314","Showtime":"2026-08-04T17:30:00+00:00","SourceDate":"2026-08-04","SourceProgrammingDate":"2026-08-04","ScreenName":"STANDARD","SeatsAvailable":73,"SessionAttributesNames":["STANDARD"],"TimeSlot":"Primetime","Status":"","ExperienceCode":"STD","IsAvailableForOffer":false,"Comment":""},{"CinemaId":"0007","ScheduledFilmId":"HO00015860","SessionId":"195283","Showtime":"2026-08-04T19:30:00+00:00","SourceDate":"2026-08-04","SourceProgrammingDate":"2026-08-04","ScreenName":"STANDARD","SeatsAvailable":41,"SessionAttributesNames":["STANDARD"],"TimeSlot":"Primetime","Status":"","ExperienceCode":"STD","IsAvailableForOffer":false,"Comment":""},{"CinemaId":"0007","ScheduledFilmId":"HO00015860","SessionId":"195315","Showtime":"2026-08-04T20:30:00+00:00","SourceDate":"2026-08-04","SourceProgrammingDate":"2026-08-04","ScreenName":"STANDARD","SeatsAvailable":111,"SessionAttributesNames":["STANDARD"],"TimeSlot":"Primetime","Status":"","ExperienceCode":"STD","IsAvailableForOffer":false,"Comment":""},{"CinemaId":"0007","ScheduledFilmId":"HO00015860","SessionId":"195284","Showtime":"2026-08-04T22:30:00+00:00","SourceDate":"2026-08-04","SourceProgrammingDate":"2026-08-04","ScreenName":"STANDARD","SeatsAvailable":67,"SessionAttributesNames":["STANDARD"],"TimeSlot":"Primetime","Status":"","ExperienceCode":"STD","IsAvailableForOffer":false,"Comment":""},{"CinemaId":"0007","ScheduledFilmId":"HO00015860","SessionId":"195316","Showtime":"2026-08-04T23:30:00+00:00","SourceDate":"2026-08-04","SourceProgrammingDate":"2026-08-04","ScreenName":"STANDARD","SeatsAvailable":92,"SessionAttributesNames":["STANDARD"],"TimeSlot":"LateNight","Status":"","ExperienceCode":"STD","IsAvailableForOffer":false,"Comment":""}]}
