{"version":"20260717-a97029fceaf39797","cinemaId":"0046","programmingDate":"2026-07-18","sessions":[{"CinemaId":"0046","ScheduledFilmId":"HO00015724","SessionId":"299803","Showtime":"2026-07-18T08:50:00+00:00","SourceDate":"2026-07-18","SourceProgrammingDate":"2026-07-18","ScreenName":"STANDARD","SeatsAvailable":120,"SessionAttributesNames":["STANDARD"],"TimeSlot":"Morning","Status":"","ExperienceCode":"STD","IsAvailableForOffer":false,"Comment":""},{"CinemaId":"0046","ScheduledFilmId":"HO00015724","SessionId":"299515","Showtime":"2026-07-18T09:40:00+00:00","SourceDate":"2026-07-18","SourceProgrammingDate":"2026-07-18","ScreenName":"KIDS","SeatsAvailable":141,"SessionAttributesNames":["KIDS"],"TimeSlot":"Morning","Status":"","ExperienceCode":"KIDS","IsAvailableForOffer":false,"Comment":""},{"CinemaId":"0046","ScheduledFilmId":"HO00015724","SessionId":"299981","Showtime":"2026-07-18T11:00:00+00:00","SourceDate":"2026-07-18","SourceProgrammingDate":"2026-07-18","ScreenName":"STANDARD","SeatsAvailable":73,"SessionAttributesNames":["STANDARD"],"TimeSlot":"Morning","Status":"","ExperienceCode":"STD","IsAvailableForOffer":false,"Comment":""},{"CinemaId":"0046","ScheduledFilmId":"HO00015724","SessionId":"299516","Showtime":"2026-07-18T11:50:00+00:00","SourceDate":"2026-07-18","SourceProgrammingDate":"2026-07-18","ScreenName":"KIDS","SeatsAvailable":125,"SessionAttributesNames":["KIDS"],"TimeSlot":"Morning","Status":"","ExperienceCode":"KIDS","IsAvailableForOffer":false,"Comment":""},{"CinemaId":"0046","ScheduledFilmId":"HO00015724","SessionId":"299982","Showtime":"2026-07-18T13:05:00+00:00","SourceDate":"2026-07-18","SourceProgrammingDate":"2026-07-18","ScreenName":"STANDARD","SeatsAvailable":161,"SessionAttributesNames":["STANDARD"],"TimeSlot":"Afternoon","Status":"","ExperienceCode":"STD","IsAvailableForOffer":false,"Comment":""},{"CinemaId":"0046","ScheduledFilmId":"HO00015724","SessionId":"299517","Showtime":"2026-07-18T14:00:00+00:00","SourceDate":"2026-07-18","SourceProgrammingDate":"2026-07-18","ScreenName":"KIDS","SeatsAvailable":107,"SessionAttributesNames":["KIDS"],"TimeSlot":"Afternoon","Status":"","ExperienceCode":"KIDS","IsAvailableForOffer":false,"Comment":""},{"CinemaId":"0046","ScheduledFilmId":"HO00015724","SessionId":"299983","Showtime":"2026-07-18T15:10:00+00:00","SourceDate":"2026-07-18","SourceProgrammingDate":"2026-07-18","ScreenName":"STANDARD","SeatsAvailable":73,"SessionAttributesNames":["STANDARD"],"TimeSlot":"Afternoon","Status":"","ExperienceCode":"STD","IsAvailableForOffer":false,"Comment":""},{"CinemaId":"0046","ScheduledFilmId":"HO00015724","SessionId":"299518","Showtime":"2026-07-18T16:10:00+00:00","SourceDate":"2026-07-18","SourceProgrammingDate":"2026-07-18","ScreenName":"KIDS","SeatsAvailable":112,"SessionAttributesNames":["KIDS"],"TimeSlot":"Afternoon","Status":"","ExperienceCode":"KIDS","IsAvailableForOffer":false,"Comment":""},{"CinemaId":"0046","ScheduledFilmId":"HO00015724","SessionId":"299984","Showtime":"2026-07-18T17:15:00+00:00","SourceDate":"2026-07-18","SourceProgrammingDate":"2026-07-18","ScreenName":"STANDARD","SeatsAvailable":153,"SessionAttributesNames":["STANDARD"],"TimeSlot":"Primetime","Status":"","ExperienceCode":"STD","IsAvailableForOffer":false,"Comment":""},{"CinemaId":"0046","ScheduledFilmId":"HO00015724","SessionId":"299519","Showtime":"2026-07-18T18:20:00+00:00","SourceDate":"2026-07-18","SourceProgrammingDate":"2026-07-18","ScreenName":"KIDS","SeatsAvailable":151,"SessionAttributesNames":["KIDS"],"TimeSlot":"Primetime","Status":"","ExperienceCode":"KIDS","IsAvailableForOffer":false,"Comment":""},{"CinemaId":"0046","ScheduledFilmId":"HO00015724","SessionId":"299985","Showtime":"2026-07-18T19:20:00+00:00","SourceDate":"2026-07-18","SourceProgrammingDate":"2026-07-18","ScreenName":"STANDARD","SeatsAvailable":57,"SessionAttributesNames":["STANDARD"],"TimeSlot":"Primetime","Status":"","ExperienceCode":"STD","IsAvailableForOffer":false,"Comment":""},{"CinemaId":"0046","ScheduledFilmId":"HO00015724","SessionId":"299520","Showtime":"2026-07-18T20:25:00+00:00","SourceDate":"2026-07-18","SourceProgrammingDate":"2026-07-18","ScreenName":"KIDS","SeatsAvailable":180,"SessionAttributesNames":["KIDS"],"TimeSlot":"Primetime","Status":"","ExperienceCode":"KIDS","IsAvailableForOffer":false,"Comment":""},{"CinemaId":"0046","ScheduledFilmId":"HO00015724","SessionId":"299521","Showtime":"2026-07-18T22:30:00+00:00","SourceDate":"2026-07-18","SourceProgrammingDate":"2026-07-18","ScreenName":"KIDS","SeatsAvailable":139,"SessionAttributesNames":["KIDS"],"TimeSlot":"Primetime","Status":"","ExperienceCode":"KIDS","IsAvailableForOffer":false,"Comment":""},{"CinemaId":"0046","ScheduledFilmId":"HO00015756","SessionId":"300172","Showtime":"2026-07-18T08:40:00+00:00","SourceDate":"2026-07-18","SourceProgrammingDate":"2026-07-18","ScreenName":"KIDS","SeatsAvailable":142,"SessionAttributesNames":["KIDS"],"TimeSlot":"Morning","Status":"","ExperienceCode":"KIDS","IsAvailableForOffer":false,"Comment":""},{"CinemaId":"0046","ScheduledFilmId":"HO00015756","SessionId":"299720","Showtime":"2026-07-18T09:30:00+00:00","SourceDate":"2026-07-18","SourceProgrammingDate":"2026-07-18","ScreenName":"STANDARD","SeatsAvailable":44,"SessionAttributesNames":["STANDARD"],"TimeSlot":"Morning","Status":"","ExperienceCode":"STD","IsAvailableForOffer":false,"Comment":""},{"CinemaId":"0046","ScheduledFilmId":"HO00015756","SessionId":"299562","Showtime":"2026-07-18T10:55:00+00:00","SourceDate":"2026-07-18","SourceProgrammingDate":"2026-07-18","ScreenName":"KIDS","SeatsAvailable":116,"SessionAttributesNames":["KIDS"],"TimeSlot":"Morning","Status":"","ExperienceCode":"KIDS","IsAvailableForOffer":false,"Comment":""},{"CinemaId":"0046","ScheduledFilmId":"HO00015756","SessionId":"299721","Showtime":"2026-07-18T11:45:00+00:00","SourceDate":"2026-07-18","SourceProgrammingDate":"2026-07-18","ScreenName":"STANDARD","SeatsAvailable":111,"SessionAttributesNames":["STANDARD"],"TimeSlot":"Morning","Status":"","ExperienceCode":"STD","IsAvailableForOffer":false,"Comment":""},{"CinemaId":"0046","ScheduledFilmId":"HO00015756","SessionId":"299563","Showtime":"2026-07-18T13:10:00+00:00","SourceDate":"2026-07-18","SourceProgrammingDate":"2026-07-18","ScreenName":"KIDS","SeatsAvailable":67,"SessionAttributesNames":["KIDS"],"TimeSlot":"Afternoon","Status":"","ExperienceCode":"KIDS","IsAvailableForOffer":false,"Comment":""},{"CinemaId":"0046","ScheduledFilmId":"HO00015756","SessionId":"299722","Showtime":"2026-07-18T14:00:00+00:00","SourceDate":"2026-07-18","SourceProgrammingDate":"2026-07-18","ScreenName":"STANDARD","SeatsAvailable":169,"SessionAttributesNames":["STANDARD"],"TimeSlot":"Afternoon","Status":"","ExperienceCode":"STD","IsAvailableForOffer":false,"Comment":""},{"CinemaId":"0046","ScheduledFilmId":"HO00015756","SessionId":"299564","Showtime":"2026-07-18T15:25:00+00:00","SourceDate":"2026-07-18","SourceProgrammingDate":"2026-07-18","ScreenName":"KIDS","SeatsAvailable":152,"SessionAttributesNames":["KIDS"],"TimeSlot":"Afternoon","Status":"","ExperienceCode":"KIDS","IsAvailableForOffer":false,"Comment":""},{"CinemaId":"0046","ScheduledFilmId":"HO00015756","SessionId":"299723","Showtime":"2026-07-18T16:15:00+00:00","SourceDate":"2026-07-18","SourceProgrammingDate":"2026-07-18","ScreenName":"STANDARD","SeatsAvailable":157,"SessionAttributesNames":["STANDARD"],"TimeSlot":"Afternoon","Status":"","ExperienceCode":"STD","IsAvailableForOffer":false,"Comment":""},{"CinemaId":"0046","ScheduledFilmId":"HO00015756","SessionId":"299565","Showtime":"2026-07-18T17:40:00+00:00","SourceDate":"2026-07-18","SourceProgrammingDate":"2026-07-18","ScreenName":"KIDS","SeatsAvailable":58,"SessionAttributesNames":["KIDS"],"TimeSlot":"Primetime","Status":"","ExperienceCode":"KIDS","IsAvailableForOffer":false,"Comment":""},{"CinemaId":"0046","ScheduledFilmId":"HO00015756","SessionId":"299724","Showtime":"2026-07-18T18:30:00+00:00","SourceDate":"2026-07-18","SourceProgrammingDate":"2026-07-18","ScreenName":"STANDARD","SeatsAvailable":71,"SessionAttributesNames":["STANDARD"],"TimeSlot":"Primetime","Status":"","ExperienceCode":"STD","IsAvailableForOffer":false,"Comment":""},{"CinemaId":"0046","ScheduledFilmId":"HO00015756","SessionId":"299566","Showtime":"2026-07-18T19:55:00+00:00","SourceDate":"2026-07-18","SourceProgrammingDate":"2026-07-18","ScreenName":"KIDS","SeatsAvailable":150,"SessionAttributesNames":["KIDS"],"TimeSlot":"Primetime","Status":"","ExperienceCode":"KIDS","IsAvailableForOffer":false,"Comment":""},{"CinemaId":"0046","ScheduledFilmId":"HO00015756","SessionId":"299567","Showtime":"2026-07-18T22:10:00+00:00","SourceDate":"2026-07-18","SourceProgrammingDate":"2026-07-18","ScreenName":"KIDS","SeatsAvailable":92,"SessionAttributesNames":["KIDS"],"TimeSlot":"Primetime","Status":"","ExperienceCode":"KIDS","IsAvailableForOffer":false,"Comment":""},{"CinemaId":"0046","ScheduledFilmId":"HO00015784","SessionId":"300026","Showtime":"2026-07-18T11:30:00+00:00","SourceDate":"2026-07-18","SourceProgrammingDate":"2026-07-18","ScreenName":"STANDARD","SeatsAvailable":177,"SessionAttributesNames":["STANDARD"],"TimeSlot":"Morning","Status":"","ExperienceCode":"STD","IsAvailableForOffer":false,"Comment":""},{"CinemaId":"0046","ScheduledFilmId":"HO00015784","SessionId":"299938","Showtime":"2026-07-18T12:40:00+00:00","SourceDate":"2026-07-18","SourceProgrammingDate":"2026-07-18","ScreenName":"STANDARD","SeatsAvailable":106,"SessionAttributesNames":["STANDARD"],"TimeSlot":"Afternoon","Status":"","ExperienceCode":"STD","IsAvailableForOffer":false,"Comment":""},{"CinemaId":"0046","ScheduledFilmId":"HO00015784","SessionId":"299940","Showtime":"2026-07-18T17:30:00+00:00","SourceDate":"2026-07-18","SourceProgrammingDate":"2026-07-18","ScreenName":"STANDARD","SeatsAvailable":103,"SessionAttributesNames":["STANDARD"],"TimeSlot":"Primetime","Status":"","ExperienceCode":"STD","IsAvailableForOffer":false,"Comment":""},{"CinemaId":"0046","ScheduledFilmId":"HO00015784","SessionId":"299942","Showtime":"2026-07-18T22:20:00+00:00","SourceDate":"2026-07-18","SourceProgrammingDate":"2026-07-18","ScreenName":"STANDARD","SeatsAvailable":40,"SessionAttributesNames":["STANDARD"],"TimeSlot":"Primetime","Status":"","ExperienceCode":"STD","IsAvailableForOffer":false,"Comment":""},{"CinemaId":"0046","ScheduledFilmId":"HO00015851","SessionId":"299767","Showtime":"2026-07-18T19:30:00+00:00","SourceDate":"2026-07-18","SourceProgrammingDate":"2026-07-18","ScreenName":"STANDARD","SeatsAvailable":70,"SessionAttributesNames":["STANDARD"],"TimeSlot":"Primetime","Status":"","ExperienceCode":"STD","IsAvailableForOffer":false,"Comment":""},{"CinemaId":"0046","ScheduledFilmId":"HO00015852","SessionId":"299677","Showtime":"2026-07-18T10:05:00+00:00","SourceDate":"2026-07-18","SourceProgrammingDate":"2026-07-18","ScreenName":"STANDARD","SeatsAvailable":172,"SessionAttributesNames":["STANDARD"],"TimeSlot":"Morning","Status":"","ExperienceCode":"STD","IsAvailableForOffer":false,"Comment":""},{"CinemaId":"0046","ScheduledFilmId":"HO00015852","SessionId":"299766","Showtime":"2026-07-18T16:45:00+00:00","SourceDate":"2026-07-18","SourceProgrammingDate":"2026-07-18","ScreenName":"STANDARD","SeatsAvailable":100,"SessionAttributesNames":["STANDARD"],"TimeSlot":"Afternoon","Status":"","ExperienceCode":"STD","IsAvailableForOffer":false,"Comment":""},{"CinemaId":"0046","ScheduledFilmId":"HO00015858","SessionId":"299763","Showtime":"2026-07-18T09:15:00+00:00","SourceDate":"2026-07-18","SourceProgrammingDate":"2026-07-18","ScreenName":"STANDARD","SeatsAvailable":113,"SessionAttributesNames":["STANDARD"],"TimeSlot":"Morning","Status":"","ExperienceCode":"STD","IsAvailableForOffer":false,"Comment":""},{"CinemaId":"0046","ScheduledFilmId":"HO00015858","SessionId":"299849","Showtime":"2026-07-18T09:45:00+00:00","SourceDate":"2026-07-18","SourceProgrammingDate":"2026-07-18","ScreenName":"STANDARD","SeatsAvailable":109,"SessionAttributesNames":["STANDARD"],"TimeSlot":"Morning","Status":"","ExperienceCode":"STD","IsAvailableForOffer":false,"Comment":""},{"CinemaId":"0046","ScheduledFilmId":"HO00015858","SessionId":"299804","Showtime":"2026-07-18T11:00:00+00:00","SourceDate":"2026-07-18","SourceProgrammingDate":"2026-07-18","ScreenName":"STANDARD","SeatsAvailable":153,"SessionAttributesNames":["STANDARD"],"TimeSlot":"Morning","Status":"","ExperienceCode":"STD","IsAvailableForOffer":false,"Comment":""},{"CinemaId":"0046","ScheduledFilmId":"HO00015858","SessionId":"299764","Showtime":"2026-07-18T11:45:00+00:00","SourceDate":"2026-07-18","SourceProgrammingDate":"2026-07-18","ScreenName":"STANDARD","SeatsAvailable":71,"SessionAttributesNames":["STANDARD"],"TimeSlot":"Morning","Status":"","ExperienceCode":"STD","IsAvailableForOffer":false,"Comment":""},{"CinemaId":"0046","ScheduledFilmId":"HO00015858","SessionId":"299850","Showtime":"2026-07-18T12:15:00+00:00","SourceDate":"2026-07-18","SourceProgrammingDate":"2026-07-18","ScreenName":"STANDARD","SeatsAvailable":177,"SessionAttributesNames":["STANDARD"],"TimeSlot":"Afternoon","Status":"","ExperienceCode":"STD","IsAvailableForOffer":false,"Comment":""},{"CinemaId":"0046","ScheduledFilmId":"HO00015858","SessionId":"299805","Showtime":"2026-07-18T13:30:00+00:00","SourceDate":"2026-07-18","SourceProgrammingDate":"2026-07-18","ScreenName":"STANDARD","SeatsAvailable":146,"SessionAttributesNames":["STANDARD"],"TimeSlot":"Afternoon","Status":"","ExperienceCode":"STD","IsAvailableForOffer":false,"Comment":""},{"CinemaId":"0046","ScheduledFilmId":"HO00015858","SessionId":"299765","Showtime":"2026-07-18T14:15:00+00:00","SourceDate":"2026-07-18","SourceProgrammingDate":"2026-07-18","ScreenName":"STANDARD","SeatsAvailable":109,"SessionAttributesNames":["STANDARD"],"TimeSlot":"Afternoon","Status":"","ExperienceCode":"STD","IsAvailableForOffer":false,"Comment":""},{"CinemaId":"0046","ScheduledFilmId":"HO00015858","SessionId":"299851","Showtime":"2026-07-18T14:45:00+00:00","SourceDate":"2026-07-18","SourceProgrammingDate":"2026-07-18","ScreenName":"STANDARD","SeatsAvailable":174,"SessionAttributesNames":["STANDARD"],"TimeSlot":"Afternoon","Status":"","ExperienceCode":"STD","IsAvailableForOffer":false,"Comment":""},{"CinemaId":"0046","ScheduledFilmId":"HO00015858","SessionId":"299806","Showtime":"2026-07-18T16:00:00+00:00","SourceDate":"2026-07-18","SourceProgrammingDate":"2026-07-18","ScreenName":"STANDARD","SeatsAvailable":124,"SessionAttributesNames":["STANDARD"],"TimeSlot":"Afternoon","Status":"","ExperienceCode":"STD","IsAvailableForOffer":false,"Comment":""},{"CinemaId":"0046","ScheduledFilmId":"HO00015858","SessionId":"299852","Showtime":"2026-07-18T17:15:00+00:00","SourceDate":"2026-07-18","SourceProgrammingDate":"2026-07-18","ScreenName":"STANDARD","SeatsAvailable":114,"SessionAttributesNames":["STANDARD"],"TimeSlot":"Primetime","Status":"","ExperienceCode":"STD","IsAvailableForOffer":false,"Comment":""},{"CinemaId":"0046","ScheduledFilmId":"HO00015858","SessionId":"299807","Showtime":"2026-07-18T18:30:00+00:00","SourceDate":"2026-07-18","SourceProgrammingDate":"2026-07-18","ScreenName":"STANDARD","SeatsAvailable":114,"SessionAttributesNames":["STANDARD"],"TimeSlot":"Primetime","Status":"","ExperienceCode":"STD","IsAvailableForOffer":false,"Comment":""},{"CinemaId":"0046","ScheduledFilmId":"HO00015858","SessionId":"299853","Showtime":"2026-07-18T19:45:00+00:00","SourceDate":"2026-07-18","SourceProgrammingDate":"2026-07-18","ScreenName":"STANDARD","SeatsAvailable":40,"SessionAttributesNames":["STANDARD"],"TimeSlot":"Primetime","Status":"","ExperienceCode":"STD","IsAvailableForOffer":false,"Comment":""},{"CinemaId":"0046","ScheduledFilmId":"HO00015858","SessionId":"299808","Showtime":"2026-07-18T21:00:00+00:00","SourceDate":"2026-07-18","SourceProgrammingDate":"2026-07-18","ScreenName":"STANDARD","SeatsAvailable":103,"SessionAttributesNames":["STANDARD"],"TimeSlot":"Primetime","Status":"","ExperienceCode":"STD","IsAvailableForOffer":false,"Comment":""},{"CinemaId":"0046","ScheduledFilmId":"HO00015858","SessionId":"299854","Showtime":"2026-07-18T22:15:00+00:00","SourceDate":"2026-07-18","SourceProgrammingDate":"2026-07-18","ScreenName":"STANDARD","SeatsAvailable":151,"SessionAttributesNames":["STANDARD"],"TimeSlot":"Primetime","Status":"","ExperienceCode":"STD","IsAvailableForOffer":false,"Comment":""},{"CinemaId":"0046","ScheduledFilmId":"HO00015886","SessionId":"300384","Showtime":"2026-07-19T00:30:00+00:00","SourceDate":"2026-07-19","SourceProgrammingDate":"2026-07-18","ScreenName":"PREMIUM","SeatsAvailable":91,"SessionAttributesNames":["PREMIUM"],"TimeSlot":"LateNight","Status":"","ExperienceCode":"PRE","IsAvailableForOffer":false,"Comment":""},{"CinemaId":"0046","ScheduledFilmId":"HO00015886","SessionId":"299937","Showtime":"2026-07-18T10:15:00+00:00","SourceDate":"2026-07-18","SourceProgrammingDate":"2026-07-18","ScreenName":"STANDARD","SeatsAvailable":162,"SessionAttributesNames":["STANDARD"],"TimeSlot":"Morning","Status":"","ExperienceCode":"STD","IsAvailableForOffer":false,"Comment":""},{"CinemaId":"0046","ScheduledFilmId":"HO00015886","SessionId":"300027","Showtime":"2026-07-18T14:00:00+00:00","SourceDate":"2026-07-18","SourceProgrammingDate":"2026-07-18","ScreenName":"STANDARD","SeatsAvailable":106,"SessionAttributesNames":["STANDARD"],"TimeSlot":"Afternoon","Status":"","ExperienceCode":"STD","IsAvailableForOffer":false,"Comment":""},{"CinemaId":"0046","ScheduledFilmId":"HO00015886","SessionId":"299939","Showtime":"2026-07-18T15:05:00+00:00","SourceDate":"2026-07-18","SourceProgrammingDate":"2026-07-18","ScreenName":"STANDARD","SeatsAvailable":178,"SessionAttributesNames":["STANDARD"],"TimeSlot":"Afternoon","Status":"","ExperienceCode":"STD","IsAvailableForOffer":false,"Comment":""},{"CinemaId":"0046","ScheduledFilmId":"HO00015886","SessionId":"300382","Showtime":"2026-07-18T19:30:00+00:00","SourceDate":"2026-07-18","SourceProgrammingDate":"2026-07-18","ScreenName":"PREMIUM","SeatsAvailable":101,"SessionAttributesNames":["PREMIUM"],"TimeSlot":"Primetime","Status":"","ExperienceCode":"PRE","IsAvailableForOffer":false,"Comment":""},{"CinemaId":"0046","ScheduledFilmId":"HO00015886","SessionId":"299941","Showtime":"2026-07-18T19:55:00+00:00","SourceDate":"2026-07-18","SourceProgrammingDate":"2026-07-18","ScreenName":"STANDARD","SeatsAvailable":179,"SessionAttributesNames":["STANDARD"],"TimeSlot":"Primetime","Status":"","ExperienceCode":"STD","IsAvailableForOffer":false,"Comment":""},{"CinemaId":"0046","ScheduledFilmId":"HO00015886","SessionId":"300383","Showtime":"2026-07-18T22:00:00+00:00","SourceDate":"2026-07-18","SourceProgrammingDate":"2026-07-18","ScreenName":"PREMIUM","SeatsAvailable":95,"SessionAttributesNames":["PREMIUM"],"TimeSlot":"Primetime","Status":"","ExperienceCode":"PRE","IsAvailableForOffer":false,"Comment":""},{"CinemaId":"0046","ScheduledFilmId":"HO00015886","SessionId":"300388","Showtime":"2026-07-18T23:30:00+00:00","SourceDate":"2026-07-18","SourceProgrammingDate":"2026-07-18","ScreenName":"STANDARD","SeatsAvailable":99,"SessionAttributesNames":["STANDARD"],"TimeSlot":"LateNight","Status":"","ExperienceCode":"STD","IsAvailableForOffer":false,"Comment":""},{"CinemaId":"0046","ScheduledFilmId":"HO00015967","SessionId":"299640","Showtime":"2026-07-19T00:00:00+00:00","SourceDate":"2026-07-19","SourceProgrammingDate":"2026-07-18","ScreenName":"STANDARD","SeatsAvailable":94,"SessionAttributesNames":["STANDARD"],"TimeSlot":"LateNight","Status":"","ExperienceCode":"STD","IsAvailableForOffer":false,"Comment":""},{"CinemaId":"0046","ScheduledFilmId":"HO00015967","SessionId":"300170","Showtime":"2026-07-19T00:55:00+00:00","SourceDate":"2026-07-19","SourceProgrammingDate":"2026-07-18","ScreenName":"STANDARD","SeatsAvailable":60,"SessionAttributesNames":["STANDARD"],"TimeSlot":"LateNight","Status":"","ExperienceCode":"STD","IsAvailableForOffer":false,"Comment":""},{"CinemaId":"0046","ScheduledFilmId":"HO00015967","SessionId":"300171","Showtime":"2026-07-18T09:20:00+00:00","SourceDate":"2026-07-18","SourceProgrammingDate":"2026-07-18","ScreenName":"STANDARD","SeatsAvailable":66,"SessionAttributesNames":["STANDARD"],"TimeSlot":"Morning","Status":"","ExperienceCode":"STD","IsAvailableForOffer":false,"Comment":""},{"CinemaId":"0046","ScheduledFilmId":"HO00015967","SessionId":"299635","Showtime":"2026-07-18T11:45:00+00:00","SourceDate":"2026-07-18","SourceProgrammingDate":"2026-07-18","ScreenName":"STANDARD","SeatsAvailable":135,"SessionAttributesNames":["STANDARD"],"TimeSlot":"Morning","Status":"","ExperienceCode":"STD","IsAvailableForOffer":false,"Comment":""},{"CinemaId":"0046","ScheduledFilmId":"HO00015967","SessionId":"299636","Showtime":"2026-07-18T14:10:00+00:00","SourceDate":"2026-07-18","SourceProgrammingDate":"2026-07-18","ScreenName":"STANDARD","SeatsAvailable":86,"SessionAttributesNames":["STANDARD"],"TimeSlot":"Afternoon","Status":"","ExperienceCode":"STD","IsAvailableForOffer":false,"Comment":""},{"CinemaId":"0046","ScheduledFilmId":"HO00015967","SessionId":"299637","Showtime":"2026-07-18T16:35:00+00:00","SourceDate":"2026-07-18","SourceProgrammingDate":"2026-07-18","ScreenName":"STANDARD","SeatsAvailable":146,"SessionAttributesNames":["STANDARD"],"TimeSlot":"Afternoon","Status":"","ExperienceCode":"STD","IsAvailableForOffer":false,"Comment":""},{"CinemaId":"0046","ScheduledFilmId":"HO00015967","SessionId":"299638","Showtime":"2026-07-18T19:10:00+00:00","SourceDate":"2026-07-18","SourceProgrammingDate":"2026-07-18","ScreenName":"STANDARD","SeatsAvailable":86,"SessionAttributesNames":["STANDARD"],"TimeSlot":"Primetime","Status":"","ExperienceCode":"STD","IsAvailableForOffer":false,"Comment":""},{"CinemaId":"0046","ScheduledFilmId":"HO00015967","SessionId":"299725","Showtime":"2026-07-18T20:45:00+00:00","SourceDate":"2026-07-18","SourceProgrammingDate":"2026-07-18","ScreenName":"STANDARD","SeatsAvailable":52,"SessionAttributesNames":["STANDARD"],"TimeSlot":"Primetime","Status":"","ExperienceCode":"STD","IsAvailableForOffer":false,"Comment":""},{"CinemaId":"0046","ScheduledFilmId":"HO00015967","SessionId":"299639","Showtime":"2026-07-18T21:35:00+00:00","SourceDate":"2026-07-18","SourceProgrammingDate":"2026-07-18","ScreenName":"STANDARD","SeatsAvailable":67,"SessionAttributesNames":["STANDARD"],"TimeSlot":"Primetime","Status":"","ExperienceCode":"STD","IsAvailableForOffer":false,"Comment":""},{"CinemaId":"0046","ScheduledFilmId":"HO00015967","SessionId":"300389","Showtime":"2026-07-18T22:30:00+00:00","SourceDate":"2026-07-18","SourceProgrammingDate":"2026-07-18","ScreenName":"STANDARD","SeatsAvailable":112,"SessionAttributesNames":["STANDARD"],"TimeSlot":"Primetime","Status":"","ExperienceCode":"STD","IsAvailableForOffer":false,"Comment":""},{"CinemaId":"0046","ScheduledFilmId":"HO00015967","SessionId":"299726","Showtime":"2026-07-18T23:10:00+00:00","SourceDate":"2026-07-18","SourceProgrammingDate":"2026-07-18","ScreenName":"STANDARD","SeatsAvailable":40,"SessionAttributesNames":["STANDARD"],"TimeSlot":"LateNight","Status":"","ExperienceCode":"STD","IsAvailableForOffer":false,"Comment":""},{"CinemaId":"0046","ScheduledFilmId":"HO00015994","SessionId":"300385","Showtime":"2026-07-19T00:45:00+00:00","SourceDate":"2026-07-19","SourceProgrammingDate":"2026-07-18","ScreenName":"STANDARD","SeatsAvailable":43,"SessionAttributesNames":["STANDARD"],"TimeSlot":"LateNight","Status":"","ExperienceCode":"STD","IsAvailableForOffer":false,"Comment":""},{"CinemaId":"0046","ScheduledFilmId":"HO00015994","SessionId":"299678","Showtime":"2026-07-18T13:00:00+00:00","SourceDate":"2026-07-18","SourceProgrammingDate":"2026-07-18","ScreenName":"STANDARD","SeatsAvailable":177,"SessionAttributesNames":["STANDARD"],"TimeSlot":"Afternoon","Status":"","ExperienceCode":"STD","IsAvailableForOffer":false,"Comment":""},{"CinemaId":"0046","ScheduledFilmId":"HO00015994","SessionId":"300321","Showtime":"2026-07-18T17:30:00+00:00","SourceDate":"2026-07-18","SourceProgrammingDate":"2026-07-18","ScreenName":"THEATRE","SeatsAvailable":23,"SessionAttributesNames":["THEATRE"],"TimeSlot":"Primetime","Status":"Almost Full","ExperienceCode":"THR","IsAvailableForOffer":false,"Comment":""},{"CinemaId":"0046","ScheduledFilmId":"HO00015994","SessionId":"299680","Showtime":"2026-07-18T18:00:00+00:00","SourceDate":"2026-07-18","SourceProgrammingDate":"2026-07-18","ScreenName":"STANDARD","SeatsAvailable":140,"SessionAttributesNames":["STANDARD"],"TimeSlot":"Primetime","Status":"","ExperienceCode":"STD","IsAvailableForOffer":false,"Comment":""},{"CinemaId":"0046","ScheduledFilmId":"HO00015994","SessionId":"299986","Showtime":"2026-07-18T21:30:00+00:00","SourceDate":"2026-07-18","SourceProgrammingDate":"2026-07-18","ScreenName":"STANDARD","SeatsAvailable":91,"SessionAttributesNames":["STANDARD"],"TimeSlot":"Primetime","Status":"","ExperienceCode":"STD","IsAvailableForOffer":false,"Comment":""},{"CinemaId":"0046","ScheduledFilmId":"HO00015994","SessionId":"299682","Showtime":"2026-07-18T23:00:00+00:00","SourceDate":"2026-07-18","SourceProgrammingDate":"2026-07-18","ScreenName":"STANDARD","SeatsAvailable":98,"SessionAttributesNames":["STANDARD"],"TimeSlot":"LateNight","Status":"","ExperienceCode":"STD","IsAvailableForOffer":false,"Comment":""},{"CinemaId":"0046","ScheduledFilmId":"HO00016029","SessionId":"299987","Showtime":"2026-07-19T00:10:00+00:00","SourceDate":"2026-07-19","SourceProgrammingDate":"2026-07-18","ScreenName":"STANDARD","SeatsAvailable":156,"SessionAttributesNames":["STANDARD"],"TimeSlot":"LateNight","Status":"","ExperienceCode":"STD","IsAvailableForOffer":false,"Comment":""},{"CinemaId":"0046","ScheduledFilmId":"HO00016029","SessionId":"299679","Showtime":"2026-07-18T15:40:00+00:00","SourceDate":"2026-07-18","SourceProgrammingDate":"2026-07-18","ScreenName":"STANDARD","SeatsAvailable":56,"SessionAttributesNames":["STANDARD"],"TimeSlot":"Afternoon","Status":"","ExperienceCode":"STD","IsAvailableForOffer":false,"Comment":""},{"CinemaId":"0046","ScheduledFilmId":"HO00016029","SessionId":"299681","Showtime":"2026-07-18T20:40:00+00:00","SourceDate":"2026-07-18","SourceProgrammingDate":"2026-07-18","ScreenName":"STANDARD","SeatsAvailable":151,"SessionAttributesNames":["STANDARD"],"TimeSlot":"Primetime","Status":"","ExperienceCode":"STD","IsAvailableForOffer":false,"Comment":""},{"CinemaId":"0046","ScheduledFilmId":"HO00016318","SessionId":"300201","Showtime":"2026-07-19T01:00:00+00:00","SourceDate":"2026-07-19","SourceProgrammingDate":"2026-07-18","ScreenName":"STANDARD","SeatsAvailable":143,"SessionAttributesNames":["STANDARD"],"TimeSlot":"LateNight","Status":"","ExperienceCode":"STD","IsAvailableForOffer":false,"Comment":""},{"CinemaId":"0046","ScheduledFilmId":"HO00016319","SessionId":"300275","Showtime":"2026-07-19T01:00:00+00:00","SourceDate":"2026-07-19","SourceProgrammingDate":"2026-07-18","ScreenName":"STANDARD","SeatsAvailable":162,"SessionAttributesNames":["STANDARD"],"TimeSlot":"LateNight","Status":"","ExperienceCode":"STD","IsAvailableForOffer":false,"Comment":""},{"CinemaId":"0046","ScheduledFilmId":"HO00016335","SessionId":"300173","Showtime":"2026-07-18T09:40:00+00:00","SourceDate":"2026-07-18","SourceProgrammingDate":"2026-07-18","ScreenName":"STANDARD","SeatsAvailable":125,"SessionAttributesNames":["STANDARD"],"TimeSlot":"Morning","Status":"","ExperienceCode":"STD","IsAvailableForOffer":false,"Comment":""},{"CinemaId":"0046","ScheduledFilmId":"HO00016335","SessionId":"299896","Showtime":"2026-07-18T11:55:00+00:00","SourceDate":"2026-07-18","SourceProgrammingDate":"2026-07-18","ScreenName":"STANDARD","SeatsAvailable":110,"SessionAttributesNames":["STANDARD"],"TimeSlot":"Morning","Status":"","ExperienceCode":"STD","IsAvailableForOffer":false,"Comment":""},{"CinemaId":"0046","ScheduledFilmId":"HO00016335","SessionId":"299897","Showtime":"2026-07-18T14:05:00+00:00","SourceDate":"2026-07-18","SourceProgrammingDate":"2026-07-18","ScreenName":"STANDARD","SeatsAvailable":44,"SessionAttributesNames":["STANDARD"],"TimeSlot":"Afternoon","Status":"","ExperienceCode":"STD","IsAvailableForOffer":false,"Comment":""},{"CinemaId":"0046","ScheduledFilmId":"HO00016335","SessionId":"299898","Showtime":"2026-07-18T16:15:00+00:00","SourceDate":"2026-07-18","SourceProgrammingDate":"2026-07-18","ScreenName":"STANDARD","SeatsAvailable":53,"SessionAttributesNames":["STANDARD"],"TimeSlot":"Afternoon","Status":"","ExperienceCode":"STD","IsAvailableForOffer":false,"Comment":""},{"CinemaId":"0046","ScheduledFilmId":"HO00016335","SessionId":"299899","Showtime":"2026-07-18T18:25:00+00:00","SourceDate":"2026-07-18","SourceProgrammingDate":"2026-07-18","ScreenName":"STANDARD","SeatsAvailable":162,"SessionAttributesNames":["STANDARD"],"TimeSlot":"Primetime","Status":"","ExperienceCode":"STD","IsAvailableForOffer":false,"Comment":""},{"CinemaId":"0046","ScheduledFilmId":"HO00016335","SessionId":"299900","Showtime":"2026-07-18T20:35:00+00:00","SourceDate":"2026-07-18","SourceProgrammingDate":"2026-07-18","ScreenName":"STANDARD","SeatsAvailable":76,"SessionAttributesNames":["STANDARD"],"TimeSlot":"Primetime","Status":"","ExperienceCode":"STD","IsAvailableForOffer":false,"Comment":""},{"CinemaId":"0046","ScheduledFilmId":"HO00016335","SessionId":"299901","Showtime":"2026-07-18T22:45:00+00:00","SourceDate":"2026-07-18","SourceProgrammingDate":"2026-07-18","ScreenName":"STANDARD","SeatsAvailable":74,"SessionAttributesNames":["STANDARD"],"TimeSlot":"Primetime","Status":"","ExperienceCode":"STD","IsAvailableForOffer":false,"Comment":""},{"CinemaId":"0046","ScheduledFilmId":"HO00016339","SessionId":"300202","Showtime":"2026-07-19T00:00:00+00:00","SourceDate":"2026-07-19","SourceProgrammingDate":"2026-07-18","ScreenName":"STANDARD","SeatsAvailable":42,"SessionAttributesNames":["STANDARD"],"TimeSlot":"LateNight","Status":"","ExperienceCode":"STD","IsAvailableForOffer":false,"Comment":""},{"CinemaId":"0046","ScheduledFilmId":"HO00016339","SessionId":"299293","Showtime":"2026-07-19T00:20:00+00:00","SourceDate":"2026-07-19","SourceProgrammingDate":"2026-07-18","ScreenName":"THEATRE","SeatsAvailable":131,"SessionAttributesNames":["THEATRE"],"TimeSlot":"LateNight","Status":"","ExperienceCode":"THR","IsAvailableForOffer":false,"Comment":""},{"CinemaId":"0046","ScheduledFilmId":"HO00016339","SessionId":"299480","Showtime":"2026-07-19T00:30:00+00:00","SourceDate":"2026-07-19","SourceProgrammingDate":"2026-07-18","ScreenName":"Couch - 2 Seater","SeatsAvailable":136,"SessionAttributesNames":["Couch - 2 Seater"],"TimeSlot":"LateNight","Status":"","ExperienceCode":"COUCH","IsAvailableForOffer":false,"Comment":""},{"CinemaId":"0046","ScheduledFilmId":"HO00016339","SessionId":"299294","Showtime":"2026-07-19T01:15:00+00:00","SourceDate":"2026-07-19","SourceProgrammingDate":"2026-07-18","ScreenName":"THEATRE","SeatsAvailable":104,"SessionAttributesNames":["THEATRE"],"TimeSlot":"LateNight","Status":"","ExperienceCode":"THR","IsAvailableForOffer":false,"Comment":""},{"CinemaId":"0046","ScheduledFilmId":"HO00016339","SessionId":"299108","Showtime":"2026-07-19T01:30:00+00:00","SourceDate":"2026-07-19","SourceProgrammingDate":"2026-07-18","ScreenName":"IMAX","SeatsAvailable":148,"SessionAttributesNames":["IMAX"],"TimeSlot":"LateNight","Status":"","ExperienceCode":"IMAX","IsAvailableForOffer":false,"Comment":""},{"CinemaId":"0046","ScheduledFilmId":"HO00016339","SessionId":"299103","Showtime":"2026-07-18T08:00:00+00:00","SourceDate":"2026-07-18","SourceProgrammingDate":"2026-07-18","ScreenName":"IMAX","SeatsAvailable":146,"SessionAttributesNames":["IMAX"],"TimeSlot":"Morning","Status":"","ExperienceCode":"IMAX","IsAvailableForOffer":false,"Comment":""},{"CinemaId":"0046","ScheduledFilmId":"HO00016339","SessionId":"299601","Showtime":"2026-07-18T08:30:00+00:00","SourceDate":"2026-07-18","SourceProgrammingDate":"2026-07-18","ScreenName":"STANDARD","SeatsAvailable":139,"SessionAttributesNames":["STANDARD"],"TimeSlot":"Morning","Status":"","ExperienceCode":"STD","IsAvailableForOffer":false,"Comment":""},{"CinemaId":"0046","ScheduledFilmId":"HO00016339","SessionId":"299173","Showtime":"2026-07-18T09:00:00+00:00","SourceDate":"2026-07-18","SourceProgrammingDate":"2026-07-18","ScreenName":"PREMIUM","SeatsAvailable":170,"SessionAttributesNames":["PREMIUM"],"TimeSlot":"Morning","Status":"","ExperienceCode":"PRE","IsAvailableForOffer":false,"Comment":""},{"CinemaId":"0046","ScheduledFilmId":"HO00016339","SessionId":"300263","Showtime":"2026-07-18T09:00:00+00:00","SourceDate":"2026-07-18","SourceProgrammingDate":"2026-07-18","ScreenName":"THEATRE","SeatsAvailable":20,"SessionAttributesNames":["THEATRE"],"TimeSlot":"Morning","Status":"Almost Full","ExperienceCode":"THR","IsAvailableForOffer":false,"Comment":""},{"CinemaId":"0046","ScheduledFilmId":"HO00016339","SessionId":"299138","Showtime":"2026-07-18T10:00:00+00:00","SourceDate":"2026-07-18","SourceProgrammingDate":"2026-07-18","ScreenName":"STANDARD","SeatsAvailable":120,"SessionAttributesNames":["STANDARD"],"TimeSlot":"Morning","Status":"","ExperienceCode":"STD","IsAvailableForOffer":false,"Comment":""},{"CinemaId":"0046","ScheduledFilmId":"HO00016339","SessionId":"299281","Showtime":"2026-07-18T10:00:00+00:00","SourceDate":"2026-07-18","SourceProgrammingDate":"2026-07-18","ScreenName":"THEATRE","SeatsAvailable":121,"SessionAttributesNames":["THEATRE"],"TimeSlot":"Morning","Status":"","ExperienceCode":"THR","IsAvailableForOffer":false,"Comment":""},{"CinemaId":"0046","ScheduledFilmId":"HO00016339","SessionId":"299476","Showtime":"2026-07-18T10:30:00+00:00","SourceDate":"2026-07-18","SourceProgrammingDate":"2026-07-18","ScreenName":"Couch - 2 Seater","SeatsAvailable":118,"SessionAttributesNames":["Couch - 2 Seater"],"TimeSlot":"Morning","Status":"","ExperienceCode":"COUCH","IsAvailableForOffer":false,"Comment":""},{"CinemaId":"0046","ScheduledFilmId":"HO00016339","SessionId":"299285","Showtime":"2026-07-18T10:30:00+00:00","SourceDate":"2026-07-18","SourceProgrammingDate":"2026-07-18","ScreenName":"THEATRE","SeatsAvailable":54,"SessionAttributesNames":["THEATRE"],"TimeSlot":"Morning","Status":"","ExperienceCode":"THR","IsAvailableForOffer":false,"Comment":""},{"CinemaId":"0046","ScheduledFilmId":"HO00016339","SessionId":"299104","Showtime":"2026-07-18T11:30:00+00:00","SourceDate":"2026-07-18","SourceProgrammingDate":"2026-07-18","ScreenName":"IMAX","SeatsAvailable":105,"SessionAttributesNames":["IMAX"],"TimeSlot":"Morning","Status":"","ExperienceCode":"IMAX","IsAvailableForOffer":false,"Comment":""},{"CinemaId":"0046","ScheduledFilmId":"HO00016339","SessionId":"299602","Showtime":"2026-07-18T12:00:00+00:00","SourceDate":"2026-07-18","SourceProgrammingDate":"2026-07-18","ScreenName":"STANDARD","SeatsAvailable":86,"SessionAttributesNames":["STANDARD"],"TimeSlot":"Afternoon","Status":"","ExperienceCode":"STD","IsAvailableForOffer":false,"Comment":""},{"CinemaId":"0046","ScheduledFilmId":"HO00016339","SessionId":"299277","Showtime":"2026-07-18T12:00:00+00:00","SourceDate":"2026-07-18","SourceProgrammingDate":"2026-07-18","ScreenName":"THEATRE","SeatsAvailable":113,"SessionAttributesNames":["THEATRE"],"TimeSlot":"Afternoon","Status":"","ExperienceCode":"THR","IsAvailableForOffer":false,"Comment":""},{"CinemaId":"0046","ScheduledFilmId":"HO00016339","SessionId":"299174","Showtime":"2026-07-18T12:30:00+00:00","SourceDate":"2026-07-18","SourceProgrammingDate":"2026-07-18","ScreenName":"PREMIUM","SeatsAvailable":97,"SessionAttributesNames":["PREMIUM"],"TimeSlot":"Afternoon","Status":"","ExperienceCode":"PRE","IsAvailableForOffer":false,"Comment":""},{"CinemaId":"0046","ScheduledFilmId":"HO00016339","SessionId":"300264","Showtime":"2026-07-18T12:50:00+00:00","SourceDate":"2026-07-18","SourceProgrammingDate":"2026-07-18","ScreenName":"THEATRE","SeatsAvailable":16,"SessionAttributesNames":["THEATRE"],"TimeSlot":"Afternoon","Status":"Almost Full","ExperienceCode":"THR","IsAvailableForOffer":false,"Comment":""},{"CinemaId":"0046","ScheduledFilmId":"HO00016339","SessionId":"299139","Showtime":"2026-07-18T13:30:00+00:00","SourceDate":"2026-07-18","SourceProgrammingDate":"2026-07-18","ScreenName":"STANDARD","SeatsAvailable":50,"SessionAttributesNames":["STANDARD"],"TimeSlot":"Afternoon","Status":"","ExperienceCode":"STD","IsAvailableForOffer":false,"Comment":""},{"CinemaId":"0046","ScheduledFilmId":"HO00016339","SessionId":"299282","Showtime":"2026-07-18T13:35:00+00:00","SourceDate":"2026-07-18","SourceProgrammingDate":"2026-07-18","ScreenName":"THEATRE","SeatsAvailable":94,"SessionAttributesNames":["THEATRE"],"TimeSlot":"Afternoon","Status":"","ExperienceCode":"THR","IsAvailableForOffer":false,"Comment":""},{"CinemaId":"0046","ScheduledFilmId":"HO00016339","SessionId":"299477","Showtime":"2026-07-18T14:00:00+00:00","SourceDate":"2026-07-18","SourceProgrammingDate":"2026-07-18","ScreenName":"Couch - 2 Seater","SeatsAvailable":161,"SessionAttributesNames":["Couch - 2 Seater"],"TimeSlot":"Afternoon","Status":"","ExperienceCode":"COUCH","IsAvailableForOffer":false,"Comment":""},{"CinemaId":"0046","ScheduledFilmId":"HO00016339","SessionId":"299286","Showtime":"2026-07-18T14:20:00+00:00","SourceDate":"2026-07-18","SourceProgrammingDate":"2026-07-18","ScreenName":"THEATRE","SeatsAvailable":92,"SessionAttributesNames":["THEATRE"],"TimeSlot":"Afternoon","Status":"","ExperienceCode":"THR","IsAvailableForOffer":false,"Comment":""},{"CinemaId":"0046","ScheduledFilmId":"HO00016339","SessionId":"299105","Showtime":"2026-07-18T15:00:00+00:00","SourceDate":"2026-07-18","SourceProgrammingDate":"2026-07-18","ScreenName":"IMAX","SeatsAvailable":57,"SessionAttributesNames":["IMAX"],"TimeSlot":"Afternoon","Status":"","ExperienceCode":"IMAX","IsAvailableForOffer":false,"Comment":""},{"CinemaId":"0046","ScheduledFilmId":"HO00016339","SessionId":"299603","Showtime":"2026-07-18T15:30:00+00:00","SourceDate":"2026-07-18","SourceProgrammingDate":"2026-07-18","ScreenName":"STANDARD","SeatsAvailable":104,"SessionAttributesNames":["STANDARD"],"TimeSlot":"Afternoon","Status":"","ExperienceCode":"STD","IsAvailableForOffer":false,"Comment":""},{"CinemaId":"0046","ScheduledFilmId":"HO00016339","SessionId":"299278","Showtime":"2026-07-18T15:40:00+00:00","SourceDate":"2026-07-18","SourceProgrammingDate":"2026-07-18","ScreenName":"THEATRE","SeatsAvailable":129,"SessionAttributesNames":["THEATRE"],"TimeSlot":"Afternoon","Status":"","ExperienceCode":"THR","IsAvailableForOffer":false,"Comment":""},{"CinemaId":"0046","ScheduledFilmId":"HO00016339","SessionId":"300381","Showtime":"2026-07-18T16:00:00+00:00","SourceDate":"2026-07-18","SourceProgrammingDate":"2026-07-18","ScreenName":"PREMIUM","SeatsAvailable":149,"SessionAttributesNames":["PREMIUM"],"TimeSlot":"Afternoon","Status":"","ExperienceCode":"PRE","IsAvailableForOffer":false,"Comment":""},{"CinemaId":"0046","ScheduledFilmId":"HO00016339","SessionId":"300028","Showtime":"2026-07-18T16:30:00+00:00","SourceDate":"2026-07-18","SourceProgrammingDate":"2026-07-18","ScreenName":"STANDARD","SeatsAvailable":119,"SessionAttributesNames":["STANDARD"],"TimeSlot":"Afternoon","Status":"","ExperienceCode":"STD","IsAvailableForOffer":false,"Comment":""},{"CinemaId":"0046","ScheduledFilmId":"HO00016339","SessionId":"299140","Showtime":"2026-07-18T17:00:00+00:00","SourceDate":"2026-07-18","SourceProgrammingDate":"2026-07-18","ScreenName":"STANDARD","SeatsAvailable":91,"SessionAttributesNames":["STANDARD"],"TimeSlot":"Primetime","Status":"","ExperienceCode":"STD","IsAvailableForOffer":false,"Comment":""},{"CinemaId":"0046","ScheduledFilmId":"HO00016339","SessionId":"299283","Showtime":"2026-07-18T17:10:00+00:00","SourceDate":"2026-07-18","SourceProgrammingDate":"2026-07-18","ScreenName":"THEATRE","SeatsAvailable":43,"SessionAttributesNames":["THEATRE"],"TimeSlot":"Primetime","Status":"","ExperienceCode":"THR","IsAvailableForOffer":false,"Comment":""},{"CinemaId":"0046","ScheduledFilmId":"HO00016339","SessionId":"299478","Showtime":"2026-07-18T17:30:00+00:00","SourceDate":"2026-07-18","SourceProgrammingDate":"2026-07-18","ScreenName":"Couch - 2 Seater","SeatsAvailable":63,"SessionAttributesNames":["Couch - 2 Seater"],"TimeSlot":"Primetime","Status":"","ExperienceCode":"COUCH","IsAvailableForOffer":false,"Comment":""},{"CinemaId":"0046","ScheduledFilmId":"HO00016339","SessionId":"299287","Showtime":"2026-07-18T18:00:00+00:00","SourceDate":"2026-07-18","SourceProgrammingDate":"2026-07-18","ScreenName":"THEATRE","SeatsAvailable":107,"SessionAttributesNames":["THEATRE"],"TimeSlot":"Primetime","Status":"","ExperienceCode":"THR","IsAvailableForOffer":false,"Comment":""},{"CinemaId":"0046","ScheduledFilmId":"HO00016339","SessionId":"299106","Showtime":"2026-07-18T18:30:00+00:00","SourceDate":"2026-07-18","SourceProgrammingDate":"2026-07-18","ScreenName":"IMAX","SeatsAvailable":50,"SessionAttributesNames":["IMAX"],"TimeSlot":"Primetime","Status":"","ExperienceCode":"IMAX","IsAvailableForOffer":false,"Comment":""},{"CinemaId":"0046","ScheduledFilmId":"HO00016339","SessionId":"299604","Showtime":"2026-07-18T19:00:00+00:00","SourceDate":"2026-07-18","SourceProgrammingDate":"2026-07-18","ScreenName":"STANDARD","SeatsAvailable":47,"SessionAttributesNames":["STANDARD"],"TimeSlot":"Primetime","Status":"","ExperienceCode":"STD","IsAvailableForOffer":false,"Comment":""},{"CinemaId":"0046","ScheduledFilmId":"HO00016339","SessionId":"299279","Showtime":"2026-07-18T19:20:00+00:00","SourceDate":"2026-07-18","SourceProgrammingDate":"2026-07-18","ScreenName":"THEATRE","SeatsAvailable":81,"SessionAttributesNames":["THEATRE"],"TimeSlot":"Primetime","Status":"","ExperienceCode":"THR","IsAvailableForOffer":false,"Comment":""},{"CinemaId":"0046","ScheduledFilmId":"HO00016339","SessionId":"300029","Showtime":"2026-07-18T20:00:00+00:00","SourceDate":"2026-07-18","SourceProgrammingDate":"2026-07-18","ScreenName":"STANDARD","SeatsAvailable":111,"SessionAttributesNames":["STANDARD"],"TimeSlot":"Primetime","Status":"","ExperienceCode":"STD","IsAvailableForOffer":false,"Comment":""},{"CinemaId":"0046","ScheduledFilmId":"HO00016339","SessionId":"300266","Showtime":"2026-07-18T20:15:00+00:00","SourceDate":"2026-07-18","SourceProgrammingDate":"2026-07-18","ScreenName":"THEATRE","SeatsAvailable":26,"SessionAttributesNames":["THEATRE"],"TimeSlot":"Primetime","Status":"Almost Full","ExperienceCode":"THR","IsAvailableForOffer":false,"Comment":""},{"CinemaId":"0046","ScheduledFilmId":"HO00016339","SessionId":"299141","Showtime":"2026-07-18T20:30:00+00:00","SourceDate":"2026-07-18","SourceProgrammingDate":"2026-07-18","ScreenName":"STANDARD","SeatsAvailable":159,"SessionAttributesNames":["STANDARD"],"TimeSlot":"Primetime","Status":"","ExperienceCode":"STD","IsAvailableForOffer":false,"Comment":""},{"CinemaId":"0046","ScheduledFilmId":"HO00016339","SessionId":"299284","Showtime":"2026-07-18T20:45:00+00:00","SourceDate":"2026-07-18","SourceProgrammingDate":"2026-07-18","ScreenName":"THEATRE","SeatsAvailable":8,"SessionAttributesNames":["THEATRE"],"TimeSlot":"Primetime","Status":"Almost Full","ExperienceCode":"THR","IsAvailableForOffer":false,"Comment":""},{"CinemaId":"0046","ScheduledFilmId":"HO00016339","SessionId":"299479","Showtime":"2026-07-18T21:00:00+00:00","SourceDate":"2026-07-18","SourceProgrammingDate":"2026-07-18","ScreenName":"Couch - 2 Seater","SeatsAvailable":167,"SessionAttributesNames":["Couch - 2 Seater"],"TimeSlot":"Primetime","Status":"","ExperienceCode":"COUCH","IsAvailableForOffer":false,"Comment":""},{"CinemaId":"0046","ScheduledFilmId":"HO00016339","SessionId":"299288","Showtime":"2026-07-18T21:40:00+00:00","SourceDate":"2026-07-18","SourceProgrammingDate":"2026-07-18","ScreenName":"THEATRE","SeatsAvailable":117,"SessionAttributesNames":["THEATRE"],"TimeSlot":"Primetime","Status":"","ExperienceCode":"THR","IsAvailableForOffer":false,"Comment":""},{"CinemaId":"0046","ScheduledFilmId":"HO00016339","SessionId":"299107","Showtime":"2026-07-18T22:00:00+00:00","SourceDate":"2026-07-18","SourceProgrammingDate":"2026-07-18","ScreenName":"IMAX","SeatsAvailable":88,"SessionAttributesNames":["IMAX"],"TimeSlot":"Primetime","Status":"","ExperienceCode":"IMAX","IsAvailableForOffer":false,"Comment":""},{"CinemaId":"0046","ScheduledFilmId":"HO00016339","SessionId":"299605","Showtime":"2026-07-18T22:30:00+00:00","SourceDate":"2026-07-18","SourceProgrammingDate":"2026-07-18","ScreenName":"STANDARD","SeatsAvailable":46,"SessionAttributesNames":["STANDARD"],"TimeSlot":"Primetime","Status":"","ExperienceCode":"STD","IsAvailableForOffer":false,"Comment":""},{"CinemaId":"0046","ScheduledFilmId":"HO00016339","SessionId":"300167","Showtime":"2026-07-18T23:00:00+00:00","SourceDate":"2026-07-18","SourceProgrammingDate":"2026-07-18","ScreenName":"THEATRE","SeatsAvailable":114,"SessionAttributesNames":["THEATRE"],"TimeSlot":"LateNight","Status":"","ExperienceCode":"THR","IsAvailableForOffer":false,"Comment":""},{"CinemaId":"0046","ScheduledFilmId":"HO00016339","SessionId":"300030","Showtime":"2026-07-18T23:30:00+00:00","SourceDate":"2026-07-18","SourceProgrammingDate":"2026-07-18","ScreenName":"STANDARD","SeatsAvailable":177,"SessionAttributesNames":["STANDARD"],"TimeSlot":"LateNight","Status":"","ExperienceCode":"STD","IsAvailableForOffer":false,"Comment":""},{"CinemaId":"0046","ScheduledFilmId":"HO00016339","SessionId":"300267","Showtime":"2026-07-18T23:55:00+00:00","SourceDate":"2026-07-18","SourceProgrammingDate":"2026-07-18","ScreenName":"THEATRE","SeatsAvailable":117,"SessionAttributesNames":["THEATRE"],"TimeSlot":"LateNight","Status":"","ExperienceCode":"THR","IsAvailableForOffer":false,"Comment":""}]}
